{
  "list": [
    {
      "date": "2014-02-07T00:00:00+02:00",
      "datestring": "7.2.2014",
      "id": "s1305782767339",
      "likes": 33000,
      "pic": "http://www.hs.fi/webkuva/sarjis/560/1305782767404?ts=841"
    },
    {
      "date": "2013-06-26T00:00:00+03:00",
      "datestring": "26.6.2013",
      "id": "s1305691746442",
      "likes": 28000,
      "pic": "http://www.hs.fi/webkuva/sarjis/560/1305691746453?ts=686"
    },
    {
      "date": "2014-06-18T00:00:00+03:00",
      "datestring": "18.6.2014",
      "id": "s1305837374937",
      "likes": 27000,
      "pic": "http://www.hs.fi/webkuva/sarjis/560/1305837374938?ts=106"
    },
    {
      "date": "2014-02-28T00:00:00+02:00",
      "datestring": "28.2.2014",
      "id": "s1305792784621",
      "likes": 27000,
      "pic": "http://www.hs.fi/webkuva/sarjis/560/1305792784666?ts=711"
    },
    {
      "date": "2014-08-16T00:00:00+03:00",
      "datestring": "16.8.2014",
      "id": "s1305860739486",
      "likes": 22000,
      "pic": "http://www.hs.fi/webkuva/sarjis/560/1305860739487?ts=327"
    },
    {
      "date": "2013-12-14T00:00:00+02:00",
      "datestring": "14.12.2013",
      "id": "s1305760258524",
      "likes": 22000,
      "pic": "http://www.hs.fi/webkuva/sarjis/560/1305760258619?ts=529"
    },
    {
      "date": "2013-04-13T00:00:00+03:00",
      "datestring": "13.4.2013",
      "id": "s1305667650497",
      "likes": 21000,
      "pic": "http://www.hs.fi/webkuva/sarjis/560/1305667650573?ts=184"
    },
    {
      "date": "2014-05-22T00:00:00+03:00",
      "datestring": "22.5.2014",
      "id": "s1305827135373",
      "likes": 19000,
      "pic": "http://www.hs.fi/webkuva/sarjis/560/1305827135585?ts=209"
    },
    {
      "date": "2013-06-05T00:00:00+03:00",
      "datestring": "5.6.2013",
      "id": "s1305683957812",
      "likes": 19000,
      "pic": "http://www.hs.fi/webkuva/sarjis/560/1305683957816?ts=888"
    },
    {
      "date": "2014-04-16T00:00:00+03:00",
      "datestring": "16.4.2014",
      "id": "s1305813483263",
      "likes": 18000,
      "pic": "http://www.hs.fi/webkuva/sarjis/560/1305813483278?ts=227"
    }
  ]
}
